ratings/__init__.py
ratings/admin.py
ratings/models.py
ratings/serializers.py
ratings/tasks.py
ratings/tests.py
ratings/urls.py
ratings/views.py
ratings/migrations/0001_initial.py
ratings/migrations/0002_auto_20161012_1211.py
ratings/migrations/__init__.py
ratings/templatetags/__init__.py
ratings/templatetags/seed.py
seed_service_rating/__init__.py
seed_service_rating/celery.py
seed_service_rating/settings.py
seed_service_rating/testsettings.py
seed_service_rating/urls.py
seed_service_rating/wsgi.py
seed_service_rating-0.9.1.dist-info/DESCRIPTION.rst
seed_service_rating-0.9.1.dist-info/LICENSE.txt
seed_service_rating-0.9.1.dist-info/METADATA
seed_service_rating-0.9.1.dist-info/RECORD
seed_service_rating-0.9.1.dist-info/WHEEL
seed_service_rating-0.9.1.dist-info/metadata.json
seed_service_rating-0.9.1.dist-info/top_level.txt
