Metadata-Version: 2.0
Name: seed-service-rating
Version: 0.9.1
Summary: Seed Service Ratings mircoservice
Home-page: http://github.com/praekelt/seed-service-rating
Author: Praekelt.org
Author-email: dev@praekelt.org
License: BSD
Platform: UNKNOWN
Classifier: Development Status :: 4 - Beta
Classifier: Framework :: Django
Classifier: License :: OSI Approved :: BSD License
Classifier: Programming Language :: Python
Classifier: Programming Language :: Python :: 2.7
Classifier: Topic :: Software Development :: Libraries :: Python Modules
Requires-Dist: Django (==1.9.12)
Requires-Dist: celery (==3.1.24)
Requires-Dist: dj-database-url (==0.3.0)
Requires-Dist: django-celery (==3.1.17)
Requires-Dist: django-filter (==0.12.0)
Requires-Dist: django-rest-hooks (==1.3.1)
Requires-Dist: djangorestframework (==3.3.2)
Requires-Dist: drfdocs (==0.0.11)
Requires-Dist: freezegun (==0.3.7)
Requires-Dist: psycopg2 (==2.7.1)
Requires-Dist: pytz (==2015.7)
Requires-Dist: raven (==5.32.0)
Requires-Dist: redis (==2.10.5)
Requires-Dist: seed-services-client (>=0.29.0)
Requires-Dist: whitenoise (==2.0.6)
